exmatrix/__init__.py
exmatrix/explainablematrix.py
exmatrix-0.2.4.dist-info/LICENSE.txt
exmatrix-0.2.4.dist-info/METADATA
exmatrix-0.2.4.dist-info/WHEEL
exmatrix-0.2.4.dist-info/top_level.txt
exmatrix-0.2.4.dist-info/RECORD
