Metadata-Version: 2.2
Name: exmatrix
Version: 0.2.4
Summary: A Python package to the ExMatrix method, supporting Random Forest models interpretability.
Home-page: https://gitlab.com/popolinneto/exmatrix
Author: Mario Popolin Neto
License: Creative Commons Attribution-NonCommercial-ShareAlike 4.0 International
Classifier: License :: Free for non-commercial use
Classifier: Operating System :: OS Independent
Classifier: Programming Language :: Python :: 3
Requires-Python: >=3.6
License-File: LICENSE.txt
Requires-Dist: lrmatrix>=0.1.5
Dynamic: author
Dynamic: classifier
Dynamic: description
Dynamic: description-content-type
Dynamic: home-page
Dynamic: license
Dynamic: requires-dist
Dynamic: requires-python
Dynamic: summary
